sqlcsv
