Metadata-Version: 2.1
Name: sqlcsv
Version: 0.4.1
Summary: Import/Export data to/from relational databases using SQL statements with CSV files
Home-page: https://github.com/yubessy/sqlcsv
Author: Shotaro Tanaka
Author-email: yubessy0@gmail.com
License: MIT
Platform: UNKNOWN
